yield_module_names_and_python_file_paths.py
yield_module_names_and_python_file_paths-0.1.0a0.dist-info/licenses/LICENSE
yield_module_names_and_python_file_paths-0.1.0a0.dist-info/METADATA
yield_module_names_and_python_file_paths-0.1.0a0.dist-info/WHEEL
yield_module_names_and_python_file_paths-0.1.0a0.dist-info/top_level.txt
yield_module_names_and_python_file_paths-0.1.0a0.dist-info/RECORD
