Metadata-Version: 2.4
Name: yield-module-names-and-python-file-paths
Version: 0.1.0a0
Summary: Recursively traverses a source directory and yields tuples of Python module names as used in import statements and their corresponding file paths.
Author-email: Jifeng Wu <jifengwu2k@gmail.com>
License-Expression: MIT
Project-URL: Homepage, https://github.com/jifengwu2k/yield-module-names-and-python-file-paths
Project-URL: Bug Tracker, https://github.com/jifengwu2k/yield-module-names-and-python-file-paths/issues
Classifier: Programming Language :: Python :: 2
Classifier: Programming Language :: Python :: 3
Classifier: Operating System :: OS Independent
Requires-Python: >=2
License-File: LICENSE
Requires-Dist: typing; python_version < "3.5"
Dynamic: license-file
